format_flex/__init__.py
format_flex/data_blob.py
format_flex/generic.py
format_flex/hierarchical.py
format_flex/tabular.py
format_flex-0.0.3.dist-info/licenses/LICENSE
format_flex-0.0.3.dist-info/METADATA
format_flex-0.0.3.dist-info/WHEEL
format_flex-0.0.3.dist-info/top_level.txt
format_flex-0.0.3.dist-info/RECORD
