Metadata-Version: 2.4
Name: format_flex
Version: 0.0.3
Summary: A flexible Python library for easy handling and conversion of Hierarchical, Tabular, and Serialized data formats.
Author-email: spring <springnode@gmail.com>
License: MIT
Project-URL: Homepage, https://github.com/NLPOptimize/FormatFlex
Project-URL: Issues, https://github.com/NLPOptimize/FormatFlex/issues
Keywords: python,yaml,toml,json,csv,xml,excel,cbor,hdf5,parquet,messagepack,feather,bson,pickle,ubjson,orc,joblib,dill,cloudpickle
Classifier: Development Status :: 2 - Pre-Alpha
Classifier: Programming Language :: Python :: 3
Classifier: Operating System :: OS Independent
Requires-Python: >=3.7
License-File: LICENSE
Requires-Dist: xmltodict
Requires-Dist: pyyaml
Requires-Dist: lxml
Requires-Dist: toml
Requires-Dist: msgpack
Requires-Dist: bson
Requires-Dist: pymongo
Requires-Dist: cbor2
Requires-Dist: py-ubjson
Requires-Dist: pyarrow
Requires-Dist: pandas
Requires-Dist: orc
Requires-Dist: openpyxl
Requires-Dist: zstandard
Requires-Dist: tabulate
Requires-Dist: blosc
Requires-Dist: dill
Requires-Dist: joblib
Requires-Dist: cloudpickle
Requires-Dist: numpy
Dynamic: license-file
